global_manager/__init__.py
global_manager/global_manager_itself.py
global_manager-1.0.4.dist-info/LICENSE
global_manager-1.0.4.dist-info/METADATA
global_manager-1.0.4.dist-info/WHEEL
global_manager-1.0.4.dist-info/top_level.txt
global_manager-1.0.4.dist-info/RECORD
